{
  "Alice": {
    "weeks": {
      "Week 1": {
        "score": 45,
        "time": 308
      },
      "Week 2": {
        "score": 33,
        "time": 145
      },
      "Week 3": {
        "score": 37,
        "time": 212
      },
      "Week 4": {
        "score": 39,
        "time": 246
      }
    },
    "month": {
      "score": 154,
      "time": 911
    },
    "two_months": {
      "score": 154,
      "time": 911
    }
  },
  "Bob": {
    "weeks": {
      "Week 1": {
        "score": 50,
        "time": 283
      },
      "Week 2": {
        "score": 36,
        "time": 169
      },
      "Week 3": {
        "score": 39,
        "time": 247
      },
      "Week 4": {
        "score": 39,
        "time": 212
      }
    },
    "month": {
      "score": 164,
      "time": 911
    },
    "two_months": {
      "score": 164,
      "time": 911
    }
  },
  "Charlie": {
    "weeks": {
      "Week 1": {
        "score": 42,
        "time": 242
      },
      "Week 2": {
        "score": 41,
        "time": 236
      },
      "Week 3": {
        "score": 38,
        "time": 208
      },
      "Week 4": {
        "score": 43,
        "time": 225
      }
    },
    "month": {
      "score": 164,
      "time": 911
    },
    "two_months": {
      "score": 164,
      "time": 911
    }
  },
  "Dana": {
    "weeks": {
      "Week 1": {
        "score": 38,
        "time": 183
      },
      "Week 2": {
        "score": 40,
        "time": 225
      },
      "Week 3": {
        "score": 52,
        "time": 315
      },
      "Week 4": {
        "score": 31,
        "time": 189
      }
    },
    "month": {
      "score": 161,
      "time": 912
    },
    "two_months": {
      "score": 161,
      "time": 912
    }
  },
  "Eli": {
    "weeks": {
      "Week 1": {
        "score": 33,
        "time": 233
      },
      "Week 2": {
        "score": 37,
        "time": 300
      },
      "Week 3": {
        "score": 32,
        "time": 182
      },
      "Week 4": {
        "score": 33,
        "time": 197
      }
    },
    "month": {
      "score": 135,
      "time": 912
    },
    "two_months": {
      "score": 135,
      "time": 912
    }
  }
}